.bumpversion.cfg
.gitignore
.travis.yml
COPYING.rst
MANIFEST.in
README.rst
appveyor.yml
meta.yaml
setup.cfg
setup.py
tox.ini
src/themysto/__init__.py
src/themysto/application.py
src/themysto/install.py
src/themysto/nbextensions_injector.py
src/themysto/notebook_shim.py
src/themysto/retirer.py
src/themysto.egg-info/PKG-INFO
src/themysto.egg-info/SOURCES.txt
src/themysto.egg-info/dependency_links.txt
src/themysto.egg-info/entry_points.txt
src/themysto.egg-info/not-zip-safe
src/themysto.egg-info/requires.txt
src/themysto.egg-info/top_level.txt
src/themysto/config_examples/highlight_html_cfg.json
src/themysto/config_examples/highlight_latex_cfg.json
src/themysto/extensions/__init__.py
src/themysto/nbextensions/autosavetime/autosavetime.yaml
src/themysto/nbextensions/autosavetime/icon.png
src/themysto/nbextensions/autosavetime/main.js
src/themysto/nbextensions/autoscroll/autoscroll.yaml
src/themysto/nbextensions/autoscroll/icon.png
src/themysto/nbextensions/autoscroll/main.js
src/themysto/nbextensions/breakpoints/main.js
src/themysto/nbextensions/cellstate/main.js
src/themysto/nbextensions/chrome-clipboard/chrome-clipboard.yaml
src/themysto/nbextensions/chrome-clipboard/chrome.png
src/themysto/nbextensions/chrome-clipboard/main.js
src/themysto/nbextensions/chrome-clipboard/readme.md
src/themysto/nbextensions/code_font_size/code_font_size.js
src/themysto/nbextensions/code_font_size/code_font_size.yaml
src/themysto/nbextensions/codefolding/codefolding.yaml
src/themysto/nbextensions/codefolding/codefolding_firstline_folded.png
src/themysto/nbextensions/codefolding/codefolding_firstline_unfolded.png
src/themysto/nbextensions/codefolding/codefolding_indent_folded_1.png
src/themysto/nbextensions/codefolding/codefolding_indent_folded_2.png
src/themysto/nbextensions/codefolding/codefolding_indent_unfolded.png
src/themysto/nbextensions/codefolding/firstline-fold.js
src/themysto/nbextensions/codefolding/foldgutter.css
src/themysto/nbextensions/codefolding/icon.png
src/themysto/nbextensions/codefolding/magic-fold.js
src/themysto/nbextensions/codefolding/main.js
src/themysto/nbextensions/codefolding/readme.md
src/themysto/nbextensions/codemirrormode_skill/README.md
src/themysto/nbextensions/codemirrormode_skill/skill.js
