Metadata-Version: 1.1
Name: themysto
Version: 0.0.4
Summary: jcb91's fork of IPython-contrib-nbextensions
Home-page: https://github.com/jcb91/IPython-notebook-extensions.git
Author: IPython-contrib Developers
Author-email: joshuacookebarnes@gmail.com
License: BSD
Download-URL: https://github.com/jcb91/IPython-notebook-extensions/tarball/0.0.4
Keywords: IPython,Jupyter,notebook
Platform: UNKNOWN
Classifier: Development Status :: 1 - Planning
Classifier: Intended Audience :: End Users/Desktop
Classifier: Intended Audience :: Science/Research
Classifier: License :: OSI Approved :: BSD License
Classifier: Natural Language :: English
Classifier: Operating System :: OS Independent
Classifier: Programming Language :: JavaScript
Classifier: Programming Language :: Python
Classifier: Topic :: Utilities
